odoo/addons/sale_advance_payment/README.rst
odoo/addons/sale_advance_payment/__init__.py
odoo/addons/sale_advance_payment/__manifest__.py
odoo/addons/sale_advance_payment/i18n/es.po
odoo/addons/sale_advance_payment/i18n/fr.po
odoo/addons/sale_advance_payment/i18n/hr.po
odoo/addons/sale_advance_payment/i18n/it.po
odoo/addons/sale_advance_payment/i18n/sale_advance_payment.pot
odoo/addons/sale_advance_payment/models/__init__.py
odoo/addons/sale_advance_payment/models/account_move.py
odoo/addons/sale_advance_payment/models/payment.py
odoo/addons/sale_advance_payment/models/sale.py
odoo/addons/sale_advance_payment/readme/CONTRIBUTORS.md
odoo/addons/sale_advance_payment/readme/DESCRIPTION.md
odoo/addons/sale_advance_payment/readme/ROADMAP.md
odoo/addons/sale_advance_payment/readme/USAGE.md
odoo/addons/sale_advance_payment/security/ir.model.access.csv
odoo/addons/sale_advance_payment/static/description/icon.png
odoo/addons/sale_advance_payment/static/description/index.html
odoo/addons/sale_advance_payment/tests/__init__.py
odoo/addons/sale_advance_payment/tests/test_sale_advance_payment.py
odoo/addons/sale_advance_payment/views/account_payment.xml
odoo/addons/sale_advance_payment/views/sale_view.xml
odoo/addons/sale_advance_payment/wizard/__init__.py
odoo/addons/sale_advance_payment/wizard/sale_advance_payment_wzd.py
odoo/addons/sale_advance_payment/wizard/sale_advance_payment_wzd_view.xml
odoo_addon_sale_advance_payment-19.0.1.0.0.2.dist-info/METADATA
odoo_addon_sale_advance_payment-19.0.1.0.0.2.dist-info/WHEEL
odoo_addon_sale_advance_payment-19.0.1.0.0.2.dist-info/top_level.txt
odoo_addon_sale_advance_payment-19.0.1.0.0.2.dist-info/RECORD
